okx/__init__.py
okx/api/__init__.py
okx/api/_client.py
okx/api/account.py
okx/api/algotrade.py
okx/api/blocktrade.py
okx/api/copytrade.py
okx/api/earn.py
okx/api/fundingaccount.py
okx/api/gridtrade.py
okx/api/market.py
okx/api/public.py
okx/api/recurringbuy.py
okx/api/savings.py
okx/api/signalbottrade.py
okx/api/spreadtrade.py
okx/api/status.py
okx/api/subaccount.py
okx/api/trade.py
okx/api/tradingstatistics.py
okx/app/__init__.py
okx/app/utils.py
okx/app/account/__init__.py
okx/app/account/accountSPOT.py
okx/app/account/accountSWAP.py
okx/app/candle_server/__init__.py
okx/app/candle_server/rule.py
okx/app/candle_server/server.py
okx/app/code/__init__.py
okx/app/code/account.py
okx/app/code/execute.py
okx/app/code/market.py
okx/app/code/trade.py
okx/app/exception/__init__.py
okx/app/exception/_base.py
okx/app/exception/param.py
okx/app/exception/request.py
okx/app/exception/rule.py
okx/app/exception/unexpected.py
okx/app/market/__init__.py
okx/app/market/_base.py
okx/app/market/exchange_info.py
okx/app/market/history_candle.py
okx/app/market/ticker.py
okx/app/market/utils.py
okx/app/trade/__init__.py
okx/app/trade/tradeSPOT/__init__.py
okx/app/trade/tradeSPOT/_base.py
okx/app/trade/tradeSPOT/close.py
okx/app/trade/tradeSPOT/open.py
okx/app/trade/tradeSPOT/order.py
okx/app/trade/tradeSPOT/quantity_and_price.py
okx/app/trade/tradeSWAP/__init__.py
okx/app/trade/tradeSWAP/_base.py
okx/app/trade/tradeSWAP/close.py
okx/app/trade/tradeSWAP/open.py
okx/app/trade/tradeSWAP/order.py
okx/app/trade/tradeSWAP/quantity_and_price.py
okx-2.1.1.dist-info/METADATA
okx-2.1.1.dist-info/WHEEL
okx-2.1.1.dist-info/top_level.txt
okx-2.1.1.dist-info/RECORD
